README.md
setup.py
servustextnormaliser/__init__.py
servustextnormaliser/servustextnormaliser.py
servustextnormaliser.egg-info/PKG-INFO
servustextnormaliser.egg-info/SOURCES.txt
servustextnormaliser.egg-info/dependency_links.txt
servustextnormaliser.egg-info/requires.txt
servustextnormaliser.egg-info/top_level.txt