Metadata-Version: 2.1
Name: servustextnormaliser
Version: 0.1
Summary: Python3 module to normalise text.
Home-page: https://github.com/carlosplanchon/servustextnormaliser
Author: Carlos A. Planchón
Author-email: bubbledoloresuruguay2@gmail.com
License: GPL3
Download-URL: https://github.com/carlosplanchon/servustextnormaliser/archive/v0.1.tar.gz
Keywords: normalise,text,regex
Platform: UNKNOWN
Classifier: Intended Audience :: Developers
Classifier: Topic :: Software Development :: Build Tools
Classifier: License :: OSI Approved :: GNU General Public License v3 (GPLv3)
Classifier: Programming Language :: Python :: 3
Classifier: Programming Language :: Python :: 3.4
Classifier: Programming Language :: Python :: 3.5
Classifier: Programming Language :: Python :: 3.6
Classifier: Programming Language :: Python :: 3.7
